invenio_previewer/__init__.py
invenio_previewer/api.py
invenio_previewer/config.py
invenio_previewer/ext.py
invenio_previewer/proxies.py
invenio_previewer/utils.py
invenio_previewer/views.py
invenio_previewer/webpack.py
invenio_previewer/assets/bootstrap3/css/invenio_previewer/prismjs/simple.css
invenio_previewer/assets/bootstrap3/css/invenio_previewer/simple_image/simple_image.css
invenio_previewer/assets/bootstrap3/js/invenio_previewer/previewer_theme.js
invenio_previewer/assets/bootstrap3/js/invenio_previewer/prismjs.js
invenio_previewer/assets/bootstrap3/js/invenio_previewer/csv_previewer/init.js
invenio_previewer/assets/bootstrap3/scss/invenio_previewer/prismjs.scss
invenio_previewer/assets/bootstrap3/scss/invenio_previewer/simple_image.scss
invenio_previewer/assets/bootstrap3/scss/invenio_previewer/style.scss
invenio_previewer/assets/bootstrap3/scss/invenio_previewer/web_archive.scss
invenio_previewer/assets/semantic-ui/css/invenio_previewer/prismjs/simple.css
invenio_previewer/assets/semantic-ui/css/invenio_previewer/simple_image/simple_image.css
invenio_previewer/assets/semantic-ui/js/invenio_previewer/bottom.js
invenio_previewer/assets/semantic-ui/js/invenio_previewer/previewer_theme.js
invenio_previewer/assets/semantic-ui/js/invenio_previewer/prismjs.js
invenio_previewer/assets/semantic-ui/js/invenio_previewer/csv_previewer/init.js
invenio_previewer/assets/semantic-ui/scss/invenio_previewer/audio_videojs.scss
invenio_previewer/assets/semantic-ui/scss/invenio_previewer/bottom.scss
invenio_previewer/assets/semantic-ui/scss/invenio_previewer/prismjs.scss
invenio_previewer/assets/semantic-ui/scss/invenio_previewer/simple_image.scss
invenio_previewer/assets/semantic-ui/scss/invenio_previewer/style.scss
invenio_previewer/assets/semantic-ui/scss/invenio_previewer/txt.scss
invenio_previewer/assets/semantic-ui/scss/invenio_previewer/video_videojs.scss
invenio_previewer/assets/semantic-ui/scss/invenio_previewer/web_archive.scss
invenio_previewer-3.6.0.dist-info/licenses/AUTHORS.rst
invenio_previewer-3.6.0.dist-info/licenses/LICENSE
invenio_previewer-3.6.0.dist-info/METADATA
invenio_previewer-3.6.0.dist-info/WHEEL
invenio_previewer-3.6.0.dist-info/entry_points.txt
invenio_previewer-3.6.0.dist-info/top_level.txt
invenio_previewer-3.6.0.dist-info/RECORD
