Metadata-Version: 2.4
Name: invenio-previewer
Version: 3.6.0
Summary: Invenio module for previewing files.
Home-page: https://github.com/inveniosoftware/invenio-previewer
Author: CERN
Author-email: info@inveniosoftware.org
License: MIT
Keywords: invenio previewer
Platform: any
Classifier: Development Status :: 5 - Production/Stable
Requires-Python: >=3.7
License-File: LICENSE
License-File: AUTHORS.rst
Requires-Dist: charset_normalizer>=3.3.2
Requires-Dist: invenio-assets<5.0.0,>=4.0.0
Requires-Dist: invenio-base<3.0.0,>=2.3.2
Requires-Dist: invenio-formatter<4.0.0,>=3.0.0
Requires-Dist: invenio-i18n<4.0.0,>=3.0.0
Requires-Dist: invenio-pidstore<3.0.0,>=2.0.0
Requires-Dist: invenio-records-ui<3.0.0,>=2.0.0
Requires-Dist: mistune>=0.8.1
Requires-Dist: nbconvert<8,>=7
Requires-Dist: nbformat<6.0,>=5.1
Requires-Dist: lxml-html-clean>=0.1.1
Provides-Extra: tests
Requires-Dist: pytest-black-ng>=0.4.0; extra == "tests"
Requires-Dist: pytest-invenio<4.0.0,>=3.0.0; extra == "tests"
Requires-Dist: invenio-app<3.0.0,>=2.0.0; extra == "tests"
Requires-Dist: invenio-config>=1.0.3; extra == "tests"
Requires-Dist: invenio-db[postgresql,versioning]<3.0.0,>=2.0.0; extra == "tests"
Requires-Dist: invenio-files-rest<4.0.0,>=3.0.0; extra == "tests"
Requires-Dist: invenio-records-files>=1.2.1; extra == "tests"
Requires-Dist: invenio-theme<5.0.0,>=4.0.0; extra == "tests"
Requires-Dist: mock>=1.3.0; extra == "tests"
Requires-Dist: sphinx>=4.5; extra == "tests"
Provides-Extra: docs
Provides-Extra: files
Requires-Dist: invenio-files-rest>=1.3.2; extra == "files"
Requires-Dist: invenio-records-files>=1.2.1; extra == "files"
Dynamic: license-file
